{
    "21-24.04": {
        "end-of-life": "2029-05-31T00:00:00Z",
        "stable": {
            "target": "124"
        },
        "candidate": {
            "target": "124"
        },
        "beta": {
            "target": "124"
        },
        "edge": {
            "target": "124"
        }
    },
    "11-24.04": {
        "end-of-life": "2029-05-31T00:00:00Z",
        "stable": {
            "target": "125"
        },
        "candidate": {
            "target": "125"
        },
        "beta": {
            "target": "125"
        },
        "edge": {
            "target": "125"
        }
    },
    "17-24.04": {
        "end-of-life": "2029-05-31T00:00:00Z",
        "stable": {
            "target": "126"
        },
        "candidate": {
            "target": "126"
        },
        "beta": {
            "target": "126"
        },
        "edge": {
            "target": "126"
        }
    }
}