{
    "21-24.04": {
        "end-of-life": "2029-05-31T00:00:00Z",
        "stable": {
            "target": "112"
        },
        "candidate": {
            "target": "112"
        },
        "beta": {
            "target": "112"
        },
        "edge": {
            "target": "112"
        }
    },
    "11-24.04": {
        "end-of-life": "2029-05-31T00:00:00Z",
        "stable": {
            "target": "113"
        },
        "candidate": {
            "target": "113"
        },
        "beta": {
            "target": "113"
        },
        "edge": {
            "target": "113"
        }
    },
    "17-24.04": {
        "end-of-life": "2029-05-31T00:00:00Z",
        "stable": {
            "target": "114"
        },
        "candidate": {
            "target": "114"
        },
        "beta": {
            "target": "114"
        },
        "edge": {
            "target": "114"
        }
    }
}