{
    "21-24.04": {
        "end-of-life": "2029-05-31T00:00:00Z",
        "stable": {
            "target": "157"
        },
        "candidate": {
            "target": "157"
        },
        "beta": {
            "target": "157"
        },
        "edge": {
            "target": "157"
        }
    },
    "11-24.04": {
        "end-of-life": "2029-05-31T00:00:00Z",
        "stable": {
            "target": "158"
        },
        "candidate": {
            "target": "158"
        },
        "beta": {
            "target": "158"
        },
        "edge": {
            "target": "158"
        }
    },
    "17-24.04": {
        "end-of-life": "2029-05-31T00:00:00Z",
        "stable": {
            "target": "159"
        },
        "candidate": {
            "target": "159"
        },
        "beta": {
            "target": "159"
        },
        "edge": {
            "target": "159"
        }
    }
}