{
    "2.8.4-22.04": {
        "stable": {
            "target": "63"
        },
        "candidate": {
            "target": "63"
        },
        "beta": {
            "target": "63"
        },
        "edge": {
            "target": "63"
        },
        "end-of-life": "2025-03-14T00:00:00Z"
    },
    "2.8-22.04": {
        "stable": {
            "target": "63"
        },
        "candidate": {
            "target": "63"
        },
        "beta": {
            "target": "63"
        },
        "edge": {
            "target": "63"
        },
        "end-of-life": "2025-03-14T00:00:00Z"
    },
    "2-22.04": {
        "stable": {
            "target": "67"
        },
        "candidate": {
            "target": "67"
        },
        "beta": {
            "target": "67"
        },
        "edge": {
            "target": "67"
        },
        "end-of-life": "2025-03-14T00:00:00Z"
    },
    "2.9.2-22.04": {
        "stable": {
            "target": "64"
        },
        "candidate": {
            "target": "64"
        },
        "beta": {
            "target": "64"
        },
        "edge": {
            "target": "64"
        },
        "end-of-life": "2025-03-14T00:00:00Z"
    },
    "2.9-22.04": {
        "stable": {
            "target": "67"
        },
        "candidate": {
            "target": "67"
        },
        "beta": {
            "target": "67"
        },
        "edge": {
            "target": "67"
        },
        "end-of-life": "2025-03-14T00:00:00Z"
    },
    "2.9.3-22.04": {
        "stable": {
            "target": "65"
        },
        "candidate": {
            "target": "65"
        },
        "beta": {
            "target": "65"
        },
        "edge": {
            "target": "65"
        },
        "end-of-life": "2025-03-14T00:00:00Z"
    },
    "2.9.4-22.04": {
        "stable": {
            "target": "66"
        },
        "candidate": {
            "target": "66"
        },
        "beta": {
            "target": "66"
        },
        "edge": {
            "target": "66"
        },
        "end-of-life": "2025-03-14T00:00:00Z"
    },
    "2.9.5-22.04": {
        "end-of-life": "2025-03-14T00:00:00Z",
        "stable": {
            "target": "67"
        },
        "candidate": {
            "target": "67"
        },
        "beta": {
            "target": "67"
        },
        "edge": {
            "target": "67"
        }
    }
}